Metadata-Version: 2.1
Name: pyinsta
Version: 0.1
Summary: This package will help you download your favourite celebrity post and also any of your friend's profile picture.
Home-page: https://github.com/vaish1999/Download-insta-posts
Author: Vaishakh Nargund
Author-email: vaishakh.nargund1999@gmail.com
License: GPL 2.0
Download-URL: https://github.com/vaish1999/Download-insta-posts/archive/v2.0.tar.gz
Keywords: instagram,download,profile,picture,post,python
Platform: UNKNOWN
Classifier: Development Status :: 3 - Alpha
Classifier: Intended Audience :: Developers
Classifier: Topic :: Software Development :: Build Tools
Classifier: License :: OSI Approved :: GNU General Public License v2 (GPLv2)
Requires-Python: >=3.7
